[{"fixture": {"id": 157120, "referee": "Martin Atkinson, England", "timezone": "UTC", "date": "2019-11-03T16:30:00+00:00", "timestamp": 1572798600, "periods": {"first": 1572798600, "second": 1572802200}, "venue": {"id": 8560, "name": "Goodison Park", "city": "Liverpool"}, "status": {"long": "Match Finished", "short": "FT", "elapsed": 90}}, "league": {"id": 39, "name": "Premier League", "country": "England", "season": 2019, "round": "Regular Season - 11"}, "teams": {"home": {"id": 45, "name": "Everton", "winner": null}, "away": {"id": 47, "name": "Tottenham", "winner": null}}, "goals": {"home": 1, "away": 1}, "score": {"halftime": {"home": 0, "away": 0}, "fulltime": {"home": 1, "away": 1}, "extratime": {"home": null, "away": null}, "penalty": {"home": null, "away": null}}, "events": [{"time": {"elapsed": 30, "extra": null}, "team": {"id": 45, "name": "Everton"}, "player": {"id": 18769, "name": "Theo Walcott"}, "assist": {"id": null, "name": null}, "type": "Card", "detail": "Yellow Card", "comments": null}, {"time": {"elapsed": 31, "extra": null}, "team": {"id": 47, "name": "Tottenham"}, "player": {"id": 174, "name": "Christian Eriksen"}, "assist": {"id": null, "name": null}, "type": "Card", "detail": "Yellow Card", "comments": null}, {"time": {"elapsed": 63, "extra": null}, "team": {"id": 47, "name": "Tottenham"}, "player": {"id": 172, "name": "D. Alli"}, "assist": {"id": 186, "name": "Son Heung-Min"}, "type": "Goal", "detail": "Normal Goal", "comments": null}, {"time": {"elapsed": 65, "extra": null}, "team": {"id": 47, "name": "Tottenham"}, "player": {"id": 662, "name": "Tanguy Ndomb\u00e9l\u00e9"}, "assist": {"id": null, "name": null}, "type": "Card", "detail": "Yellow Card", "comments": null}, {"time": {"elapsed": 68, "extra": null}, "team": {"id": 45, "name": "Everton"}, "player": {"id": 18769, "name": "T. Walcott"}, "assist": {"id": 18768, "name": "C. Tosun"}, "type": "subst", "detail": "Substitution 1", "comments": null}, {"time": {"elapsed": 73, "extra": null}, "team": {"id": 47, "name": "Tottenham"}, "player": {"id": 662, "name": "T. Ndomb\u00e8l\u00e9"}, "assist": {"id": 1578, "name": "G. Lo Celso"}, "type": "subst", "detail": "Substitution 1", "comments": null}, {"time": {"elapsed": 79, "extra": null}, "team": {"id": 47, "name": "Tottenham"}, "player": {"id": 186, "name": "Heung-Min Son"}, "assist": {"id": null, "name": null}, "type": "Card", "detail": "Red Card", "comments": null}, {"time": {"elapsed": 83, "extra": null}, "team": {"id": 45, "name": "Everton"}, "player": {"id": 18762, "name": "T. Davies"}, "assist": {"id": 18766, "name": "D. Calvert-Lewin"}, "type": "subst", "detail": "Substitution 2", "comments": null}, {"time": {"elapsed": 84, "extra": null}, "team": {"id": 45, "name": "Everton"}, "player": {"id": 18765, "name": "Andr\u00e9 Gomes"}, "assist": {"id": 2795, "name": "G. Sigur\u00f0sson"}, "type": "subst", "detail": "Substitution 3", "comments": null}, {"time": {"elapsed": 88, "extra": null}, "team": {"id": 47, "name": "Tottenham"}, "player": {"id": 163, "name": "S. Aurier"}, "assist": {"id": 166, "name": "J. Foyth"}, "type": "subst", "detail": "Substitution 2", "comments": null}, {"time": {"elapsed": 90, "extra": 12}, "team": {"id": 47, "name": "Tottenham"}, "player": {"id": 174, "name": "C. Eriksen"}, "assist": {"id": 19032, "name": "R. Sessegnon"}, "type": "subst", "detail": "Substitution 3", "comments": null}, {"time": {"elapsed": 90, "extra": 7}, "team": {"id": 45, "name": "Everton"}, "player": {"id": 18768, "name": "C. Tosun"}, "assist": {"id": 2724, "name": "L. Digne"}, "type": "Goal", "detail": "Normal Goal", "comments": null}], "lineups": [{"team": {"id": 45, "name": "Everton", "colors": null}, "coach": {"id": 10, "name": "Marco Silva"}, "formation": "4-1-4-1", "startXI": [{"player": {"id": 2932, "name": "J. Pickford", "number": 1, "pos": "G", "grid": "1:1"}}, {"player": {"id": 102, "name": "D. Sidib\u00e9", "number": 19, "pos": "D", "grid": "2:4"}}, {"player": {"id": 2724, "name": "L. Digne", "number": 12, "pos": "D", "grid": "2:3"}}, {"player": {"id": 2484, "name": "Y. Mina", "number": 13, "pos": "D", "grid": "2:2"}}, {"player": {"id": 19150, "name": "M. Holgate", "number": 2, "pos": "D", "grid": "2:1"}}, {"player": {"id": 630, "name": "F. Delph", "number": 8, "pos": "M", "grid": "3:1"}}, {"player": {"id": 18765, "name": "Andr\u00e9 Gomes", "number": 21, "pos": "M", "grid": "4:4"}}, {"player": {"id": 1455, "name": "A. Iwobi", "number": 17, "pos": "M", "grid": "4:3"}}, {"player": {"id": 18762, "name": "T. Davies", "number": 26, "pos": "M", "grid": "4:2"}}, {"player": {"id": 18769, "name": "T. Walcott", "number": 11, "pos": "M", "grid": "4:1"}}, {"player": {"id": 2413, "name": "Richarlison", "number": 7, "pos": "F", "grid": "5:1"}}], "substitutes": [{"player": {"id": 18768, "name": "C. Tosun", "number": 14, "pos": "F", "grid": null}}, {"player": {"id": 18766, "name": "D. Calvert-Lewin", "number": 9, "pos": "F", "grid": null}}, {"player": {"id": 2795, "name": "G. Sigur\u00f0sson", "number": 10, "pos": "M", "grid": null}}, {"player": {"id": 877, "name": "M. Kean", "number": 27, "pos": "F", "grid": null}}, {"player": {"id": 2727, "name": "J. L\u00f6ssl", "number": 49, "pos": "G", "grid": null}}, {"player": {"id": 2934, "name": "M. Keane", "number": 5, "pos": "D", "grid": null}}, {"player": {"id": 18758, "name": "S. Coleman", "number": 23, "pos": "D", "grid": null}}]}, {"team": {"id": 47, "name": "Tottenham", "colors": null}, "coach": {"id": 13, "name": "M. Pochettino"}, "formation": "4-2-3-1", "startXI": [{"player": {"id": 158, "name": "P. Gazzaniga", "number": 22, "pos": "G", "grid": "1:1"}}, {"player": {"id": 162, "name": "T. Alderweireld", "number": 4, "pos": "D", "grid": "2:4"}}, {"player": {"id": 163, "name": "S. Aurier", "number": 24, "pos": "D", "grid": "2:3"}}, {"player": {"id": 164, "name": "B. Davies", "number": 33, "pos": "D", "grid": "2:2"}}, {"player": {"id": 168, "name": "D. S\u00e1nchez", "number": 6, "pos": "D", "grid": "2:1"}}, {"player": {"id": 179, "name": "M. Sissoko", "number": 17, "pos": "M", "grid": "3:2"}}, {"player": {"id": 174, "name": "C. Eriksen", "number": 23, "pos": "M", "grid": "3:1"}}, {"player": {"id": 178, "name": "Lucas Moura", "number": 27, "pos": "F", "grid": "4:3"}}, {"player": {"id": 172, "name": "D. Alli", "number": 20, "pos": "M", "grid": "4:2"}}, {"player": {"id": 662, "name": "T. Ndomb\u00e8l\u00e9", "number": 28, "pos": "M", "grid": "4:1"}}, {"player": {"id": 186, "name": "Son Heung-Min", "number": 7, "pos": "M", "grid": "5:1"}}], "substitutes": [{"player": {"id": 1578, "name": "G. Lo Celso", "number": 18, "pos": "M", "grid": null}}, {"player": {"id": 166, "name": "J. Foyth", "number": 21, "pos": "D", "grid": null}}, {"player": {"id": 19032, "name": "R. Sessegnon", "number": 19, "pos": "M", "grid": null}}, {"player": {"id": 175, "name": "E. Dier", "number": 15, "pos": "M", "grid": null}}, {"player": {"id": 149551, "name": "T. Parrott", "number": 52, "pos": "F", "grid": null}}, {"player": {"id": 182, "name": "H. Winks", "number": 8, "pos": "M", "grid": null}}, {"player": {"id": 160, "name": "M. Vorm", "number": 13, "pos": "G", "grid": null}}]}], "statistics": [{"team": {"id": 45, "name": "Everton"}, "statistics": [{"type": "Shots on Goal", "value": 3}, {"type": "Shots off Goal", "value": 3}, {"type": "Total Shots", "value": 7}, {"type": "Blocked Shots", "value": 1}, {"type": "Shots insidebox", "value": 6}, {"type": "Shots outsidebox", "value": 1}, {"type": "Fouls", "value": 9}, {"type": "Corner Kicks", "value": 5}, {"type": "Offsides", "value": 1}, {"type": "Ball Possession", "value": "47%"}, {"type": "Yellow Cards", "value": 1}, {"type": "Red Cards", "value": null}, {"type": "Goalkeeper Saves", "value": 1}, {"type": "Total passes", "value": 375}, {"type": "Passes accurate", "value": 281}, {"type": "Passes %", "value": "75%"}]}, {"team": {"id": 47, "name": "Tottenham"}, "statistics": [{"type": "Shots on Goal", "value": 2}, {"type": "Shots off Goal", "value": 2}, {"type": "Total Shots", "value": 5}, {"type": "Blocked Shots", "value": 1}, {"type": "Shots insidebox", "value": 3}, {"type": "Shots outsidebox", "value": 2}, {"type": "Fouls", "value": 8}, {"type": "Corner Kicks", "value": 2}, {"type": "Offsides", "value": 2}, {"type": "Ball Possession", "value": "53%"}, {"type": "Yellow Cards", "value": 2}, {"type": "Red Cards", "value": null}, {"type": "Goalkeeper Saves", "value": 2}, {"type": "Total passes", "value": 443}, {"type": "Passes accurate", "value": 344}, {"type": "Passes %", "value": "78%"}]}], "players": [{"team": {"id": 45, "name": "Everton", "update": "2020-09-09T07:12:46+00:00"}, "players": [{"player": {"id": 2932, "name": "Jordan Pickford"}, "statistics": [{"games": {"minutes": 90, "number": 1, "position": "G", "rating": "6.4", "captain": false, "substitute": false}, "offsides": null, "shots": {"total": 0, "on": 0}, "goals": {"total": null, "conceded": 1, "assists": null, "saves": 1}, "passes": {"total": 23, "key": 0, "accuracy": "74%"}, "tackles": {"total": null, "blocks": 0, "interceptions": 0}, "duels": {"total": 0, "won": 0}, "dribbles": {"attempts": 0, "success": 0, "past": null}, "fouls": {"drawn": 0, "committed": 0}, "cards": {"yellow": 0, "red": 0}, "penalty": {"won": null, "commited": null, "scored": 0, "missed": 0, "saved": 0}}]}, {"player": {"id": 102, "name": "Djibril Sidib\u00e9"}, "statistics": [{"games": {"minutes": 90, "number": 19, "position": "D", "rating": "7.0", "captain": false, "substitute": false}, "offsides": null, "shots": {"total": 0, "on": 0}, "goals": {"total": null, "conceded": 0, "assists": null, "saves": null}, "passes": {"total": 28, "key": 0, "accuracy": "71%"}, "tackles": {"total": 3, "blocks": 0, "interceptions": 1}, "duels": {"total": 10, "won": 6}, "dribbles": {"attempts": 2, "success": 2, "past": 1}, "fouls": {"drawn": 1, "committed": 0}, "cards": {"yellow": 0, "red": 0}, "penalty": {"won": null, "commited": null, "scored": 0, "missed": 0, "saved": null}}]}, {"player": {"id": 2484, "name": "Yerry Mina"}, "statistics": [{"games": {"minutes": 90, "number": 13, "position": "D", "rating": "7.0", "captain": false, "substitute": false}, "offsides": null, "shots": {"total": 0, "on": 0}, "goals": {"total": null, "conceded": 0, "assists": null, "saves": null}, "passes": {"total": 34, "key": 0, "accuracy": "85%"}, "tackles": {"total": 2, "blocks": 0, "interceptions": 0}, "duels": {"total": 8, "won": 6}, "dribbles": {"attempts": 0, "success": 0, "past": null}, "fouls": {"drawn": 0, "committed": 1}, "cards": {"yellow": 0, "red": 0}, "penalty": {"won": null, "commited": null, "scored": 0, "missed": 0, "saved": null}}]}, {"player": {"id": 19150, "name": "Mason Holgate"}, "statistics": [{"games": {"minutes": 90, "number": 2, "position": "D", "rating": "7.0", "captain": false, "substitute": false}, "offsides": null, "shots": {"total": 0, "on": 0}, "goals": {"total": null, "conceded": 0, "assists": null, "saves": null}, "passes": {"total": 34, "key": 0, "accuracy": "75%"}, "tackles": {"total": 1, "blocks": 1, "interceptions": 1}, "duels": {"total": 7, "won": 5}, "dribbles": {"attempts": 1, "success": 1, "past": 1}, "fouls": {"drawn": 0, "committed": 0}, "cards": {"yellow": 0, "red": 0}, "penalty": {"won": null, "commited": null, "scored": 0, "missed": 0, "saved": null}}]}, {"player": {"id": 2724, "name": "Lucas Digne"}, "statistics": [{"games": {"minutes": 90, "number": 12, "position": "D", "rating": "8.0", "captain": true, "substitute": false}, "offsides": null, "shots": {"total": 0, "on": 0}, "goals": {"total": null, "conceded": 0, "assists": 1, "saves": null}, "passes": {"total": 28, "key": 3, "accuracy": "68%"}, "tackles": {"total": 4, "blocks": 0, "interceptions": 0}, "duels": {"total": 12, "won": 8}, "dribbles": {"attempts": 1, "success": 1, "past": null}, "fouls": {"drawn": 1, "committed": 1}, "cards": {"yellow": 0, "red": 0}, "penalty": {"won": null, "commited": null, "scored": 0, "missed": 0, "saved": null}}]}, {"player": {"id": 630, "name": "Fabian Delph"}, "statistics": [{"games": {"minutes": 90, "number": 8, "position": "M", "rating": "7.2", "captain": false, "substitute": false}, "offsides": null, "shots": {"total": 0, "on": 0}, "goals": {"total": null, "conceded": 0, "assists": null, "saves": null}, "passes": {"total": 40, "key": 0, "accuracy": "85%"}, "tackles": {"total": 3, "blocks": 0, "interceptions": 1}, "duels": {"total": 13, "won": 9}, "dribbles": {"attempts": 3, "success": 3, "past": null}, "fouls": {"drawn": 1, "committed": 3}, "cards": {"yellow": 0, "red": 0}, "penalty": {"won": null, "commited": null, "scored": 0, "missed": 0, "saved": null}}]}, {"player": {"id": 18769, "name": "Theo Walcott"}, "statistics": [{"games": {"minutes": 68, "number": 11, "position": "M", "rating": "6.4", "captain": false, "substitute": false}, "offsides": null, "shots": {"total": 0, "on": 0}, "goals": {"total": null, "conceded": 0, "assists": null, "saves": null}, "passes": {"total": 3, "key": 1, "accuracy": "33%"}, "tackles": {"total": 1, "blocks": 0, "interceptions": 1}, "duels": {"total": 8, "won": 4}, "dribbles": {"attempts": 1, "success": 1, "past": 1}, "fouls": {"drawn": 1, "committed": 1}, "cards": {"yellow": 1, "red": 0}, "penalty": {"won": null, "commited": null, "scored": 0, "missed": 0, "saved": null}}]}, {"player": {"id": 18762, "name": "Tom Davies"}, "statistics": [{"games": {"minutes": 83, "number": 26, "position": "M", "rating": "7.2", "captain": false, "substitute": false}, "offsides": null, "shots": {"total": 0, "on": 0}, "goals": {"total": null, "conceded": 0, "assists": null, "saves": null}, "passes": {"total": 18, "key": 0, "accuracy": "78%"}, "tackles": {"total": 4, "blocks": 0, "interceptions": 1}, "duels": {"total": 10, "won": 7}, "dribbles": {"attempts": 2, "success": 2, "past": null}, "fouls": {"drawn": 1, "committed": 1}, "cards": {"yellow": 0, "red": 0}, "penalty": {"won": null, "commited": null, "scored": 0, "missed": 0, "saved": null}}]}, {"player": {"id": 18765, "name": "Andr\u00e9 Gomes"}, "statistics": [{"games": {"minutes": 84, "number": 21, "position": "M", "rating": "6.9", "captain": false, "substitute": false}, "offsides": null, "shots": {"total": 1, "on": 0}, "goals": {"total": null, "conceded": 0, "assists": null, "saves": null}, "passes": {"total": 25, "key": 1, "accuracy": "78%"}, "tackles": {"total": 1, "blocks": 0, "interceptions": 0}, "duels": {"total": 11, "won": 5}, "dribbles": {"attempts": 3, "success": 2, "past": 1}, "fouls": {"drawn": 1, "committed": 0}, "cards": {"yellow": 0, "red": 0}, "penalty": {"won": null, "commited": null, "scored": 0, "missed": 0, "saved": null}}]}, {"player": {"id": 1455, "name": "Alex Iwobi"}, "statistics": [{"games": {"minutes": 90, "number": 17, "position": "M", "rating": "6.7", "captain": false, "substitute": false}, "offsides": null, "shots": {"total": 0, "on": 0}, "goals": {"total": null, "conceded": 0, "assists": null, "saves": null}, "passes": {"total": 23, "key": 1, "accuracy": "79%"}, "tackles": {"total": 5, "blocks": 0, "interceptions": 1}, "duels": {"total": 14, "won": 9}, "dribbles": {"attempts": 4, "success": 3, "past": 2}, "fouls": {"drawn": 1, "committed": 0}, "cards": {"yellow": 0, "red": 0}, "penalty": {"won": null, "commited": null, "scored": 0, "missed": 0, "saved": null}}]}, {"player": {"id": 2413, "name": "Richarlison"}, "statistics": [{"games": {"minutes": 90, "number": 7, "position": "F", "rating": "6.9", "captain": false, "substitute": false}, "offsides": 1, "shots": {"total": 4, "on": 2}, "goals": {"total": null, "conceded": 0, "assists": null, "saves": null}, "passes": {"total": 16, "key": 0, "accuracy": "69%"}, "tackles": {"total": 2, "blocks": 0, "interceptions": 0}, "duels": {"total": 16, "won": 6}, "dribbles": {"attempts": 2, "success": 1, "past": 1}, "fouls": {"drawn": 1, "committed": 1}, "cards": {"yellow": 0, "red": 0}, "penalty": {"won": null, "commited": null, "scored": 0, "missed": 0, "saved": null}}]}, {"player": {"id": 2795, "name": "Gylfi Sigur\u00f0sson"}, "statistics": [{"games": {"minutes": 19, "number": 10, "position": "M", "rating": "6.7", "captain": false, "substitute": true}, "offsides": null, "shots": {"total": 0, "on": 0}, "goals": {"total": null, "conceded": 0, "assists": null, "saves": null}, "passes": {"total": 7, "key": 0, "accuracy": "77%"}, "tackles": {"total": null, "blocks": 0, "interceptions": 0}, "duels": {"total": 0, "won": 0}, "dribbles": {"attempts": 0, "success": 0, "past": null}, "fouls": {"drawn": 0, "committed": 0}, "cards": {"yellow": 0, "red": 0}, "penalty": {"won": null, "commited": null, "scored": 0, "missed": 0, "saved": null}}]}, {"player": {"id": 18768, "name": "Cenk Tosun"}, "statistics": [{"games": {"minutes": 22, "number": 14, "position": "F", "rating": "7.2", "captain": false, "substitute": true}, "offsides": null, "shots": {"total": 1, "on": 1}, "goals": {"total": 1, "conceded": 0, "assists": null, "saves": null}, "passes": {"total": 1, "key": 0, "accuracy": "20%"}, "tackles": {"total": null, "blocks": 0, "interceptions": 0}, "duels": {"total": 2, "won": 1}, "dribbles": {"attempts": 0, "success": 0, "past": null}, "fouls": {"drawn": 0, "committed": 0}, "cards": {"yellow": 0, "red": 0}, "penalty": {"won": null, "commited": null, "scored": 0, "missed": 0, "saved": null}}]}, {"player": {"id": 18766, "name": "Dominic Calvert-Lewin"}, "statistics": [{"games": {"minutes": 20, "number": 9, "position": "F", "rating": "6.0", "captain": false, "substitute": true}, "offsides": null, "shots": {"total": 1, "on": 0}, "goals": {"total": null, "conceded": 0, "assists": null, "saves": null}, "passes": {"total": 1, "key": 0, "accuracy": "50%"}, "tackles": {"total": null, "blocks": 0, "interceptions": 0}, "duels": {"total": 3, "won": 0}, "dribbles": {"attempts": 0, "success": 0, "past": null}, "fouls": {"drawn": 0, "committed": 1}, "cards": {"yellow": 0, "red": 0}, "penalty": {"won": null, "commited": null, "scored": 0, "missed": 0, "saved": null}}]}]}, {"team": {"id": 47, "name": "Tottenham", "update": "2020-09-09T07:12:46+00:00"}, "players": [{"player": {"id": 158, "name": "Paulo Gazzaniga"}, "statistics": [{"games": {"minutes": 90, "number": 22, "position": "G", "rating": "6.6", "captain": false, "substitute": false}, "offsides": null, "shots": {"total": 0, "on": 0}, "goals": {"total": null, "conceded": 1, "assists": null, "saves": 2}, "passes": {"total": 21, "key": 0, "accuracy": "67%"}, "tackles": {"total": null, "blocks": 0, "interceptions": 0}, "duels": {"total": 1, "won": 1}, "dribbles": {"attempts": 0, "success": 0, "past": null}, "fouls": {"drawn": 0, "committed": 0}, "cards": {"yellow": 0, "red": 0}, "penalty": {"won": null, "commited": null, "scored": 0, "missed": 0, "saved": 0}}]}, {"player": {"id": 163, "name": "Serge Aurier"}, "statistics": [{"games": {"minutes": 88, "number": 24, "position": "D", "rating": "7.5", "captain": false, "substitute": false}, "offsides": null, "shots": {"total": 0, "on": 0}, "goals": {"total": null, "conceded": 0, "assists": null, "saves": null}, "passes": {"total": 31, "key": 1, "accuracy": "75%"}, "tackles": {"total": 5, "blocks": 0, "interceptions": 2}, "duels": {"total": 10, "won": 8}, "dribbles": {"attempts": 1, "success": 1, "past": 1}, "fouls": {"drawn": 0, "committed": 0}, "cards": {"yellow": 0, "red": 0}, "penalty": {"won": null, "commited": null, "scored": 0, "missed": 0, "saved": null}}]}, {"player": {"id": 162, "name": "Toby Alderweireld"}, "statistics": [{"games": {"minutes": 90, "number": 4, "position": "D", "rating": "7.0", "captain": false, "substitute": false}, "offsides": null, "shots": {"total": 2, "on": 0}, "goals": {"total": null, "conceded": 0, "assists": null, "saves": null}, "passes": {"total": 56, "key": 0, "accuracy": "87%"}, "tackles": {"total": 2, "blocks": 1, "interceptions": 2}, "duels": {"total": 8, "won": 3}, "dribbles": {"attempts": 0, "success": 0, "past": 1}, "fouls": {"drawn": 0, "committed": 1}, "cards": {"yellow": 0, "red": 0}, "penalty": {"won": null, "commited": null, "scored": 0, "missed": 0, "saved": null}}]}, {"player": {"id": 168, "name": "Davinson S\u00e1nchez"}, "statistics": [{"games": {"minutes": 90, "number": 6, "position": "D", "rating": "6.9", "captain": false, "substitute": false}, "offsides": null, "shots": {"total": 0, "on": 0}, "goals": {"total": null, "conceded": 0, "assists": null, "saves": null}, "passes": {"total": 55, "key": 0, "accuracy": "85%"}, "tackles": {"total": 4, "blocks": 0, "interceptions": 1}, "duels": {"total": 8, "won": 6}, "dribbles": {"attempts": 0, "success": 0, "past": null}, "fouls": {"drawn": 0, "committed": 1}, "cards": {"yellow": 0, "red": 0}, "penalty": {"won": null, "commited": null, "scored": 0, "missed": 0, "saved": null}}]}, {"player": {"id": 164, "name": "Ben Davies"}, "statistics": [{"games": {"minutes": 90, "number": 33, "position": "D", "rating": "6.3", "captain": true, "substitute": false}, "offsides": 1, "shots": {"total": 0, "on": 0}, "goals": {"total": null, "conceded": 0, "assists": null, "saves": null}, "passes": {"total": 15, "key": 1, "accuracy": "50%"}, "tackles": {"total": null, "blocks": 0, "interceptions": 1}, "duels": {"total": 13, "won": 5}, "dribbles": {"attempts": 0, "success": 0, "past": null}, "fouls": {"drawn": 1, "committed": 3}, "cards": {"yellow": 0, "red": 0}, "penalty": {"won": null, "commited": null, "scored": 0, "missed": 0, "saved": null}}]}, {"player": {"id": 179, "name": "Moussa Sissoko"}, "statistics": [{"games": {"minutes": 90, "number": 17, "position": "M", "rating": "6.5", "captain": false, "substitute": false}, "offsides": null, "shots": {"total": 0, "on": 0}, "goals": {"total": null, "conceded": 0, "assists": null, "saves": null}, "passes": {"total": 43, "key": 0, "accuracy": "82%"}, "tackles": {"total": 1, "blocks": 0, "interceptions": 1}, "duels": {"total": 9, "won": 5}, "dribbles": {"attempts": 0, "success": 0, "past": 3}, "fouls": {"drawn": 0, "committed": 0}, "cards": {"yellow": 0, "red": 0}, "penalty": {"won": null, "commited": null, "scored": 0, "missed": 0, "saved": null}}]}, {"player": {"id": 662, "name": "Tanguy Ndomb\u00e9l\u00e9"}, "statistics": [{"games": {"minutes": 73, "number": 28, "position": "M", "rating": "6.4", "captain": false, "substitute": false}, "offsides": null, "shots": {"total": 0, "on": 0}, "goals": {"total": null, "conceded": 0, "assists": null, "saves": null}, "passes": {"total": 34, "key": 0, "accuracy": "81%"}, "tackles": {"total": null, "blocks": 0, "interceptions": 2}, "duels": {"total": 9, "won": 4}, "dribbles": {"attempts": 4, "success": 3, "past": 1}, "fouls": {"drawn": 1, "committed": 0}, "cards": {"yellow": 1, "red": 0}, "penalty": {"won": null, "commited": null, "scored": 0, "missed": 0, "saved": null}}]}, {"player": {"id": 186, "name": "Heung-Min Son"}, "statistics": [{"games": {"minutes": 79, "number": 7, "position": "M", "rating": "5.6", "captain": false, "substitute": false}, "offsides": null, "shots": {"total": 1, "on": 0}, "goals": {"total": null, "conceded": 0, "assists": 1, "saves": null}, "passes": {"total": 12, "key": 1, "accuracy": "92%"}, "tackles": {"total": null, "blocks": 0, "interceptions": 0}, "duels": {"total": 10, "won": 1}, "dribbles": {"attempts": 1, "success": 1, "past": 3}, "fouls": {"drawn": 0, "committed": 1}, "cards": {"yellow": 0, "red": 1}, "penalty": {"won": null, "commited": null, "scored": 0, "missed": 0, "saved": null}}]}, {"player": {"id": 174, "name": "Christian Eriksen"}, "statistics": [{"games": {"minutes": 89, "number": 23, "position": "M", "rating": "6.2", "captain": false, "substitute": false}, "offsides": 1, "shots": {"total": 0, "on": 0}, "goals": {"total": null, "conceded": 0, "assists": null, "saves": null}, "passes": {"total": 25, "key": 1, "accuracy": "73%"}, "tackles": {"total": null, "blocks": 0, "interceptions": 0}, "duels": {"total": 6, "won": 2}, "dribbles": {"attempts": 0, "success": 0, "past": 1}, "fouls": {"drawn": 2, "committed": 1}, "cards": {"yellow": 1, "red": 0}, "penalty": {"won": null, "commited": null, "scored": 0, "missed": 0, "saved": null}}]}, {"player": {"id": 172, "name": "Dele Alli"}, "statistics": [{"games": {"minutes": 90, "number": 20, "position": "M", "rating": "7.1", "captain": false, "substitute": false}, "offsides": null, "shots": {"total": 1, "on": 1}, "goals": {"total": 1, "conceded": 0, "assists": null, "saves": null}, "passes": {"total": 29, "key": 1, "accuracy": "70%"}, "tackles": {"total": null, "blocks": 0, "interceptions": 0}, "duels": {"total": 6, "won": 2}, "dribbles": {"attempts": 2, "success": 1, "past": 2}, "fouls": {"drawn": 0, "committed": 0}, "cards": {"yellow": 0, "red": 0}, "penalty": {"won": null, "commited": null, "scored": 0, "missed": 0, "saved": null}}]}, {"player": {"id": 178, "name": "Lucas Moura"}, "statistics": [{"games": {"minutes": 90, "number": 27, "position": "F", "rating": "6.1", "captain": false, "substitute": false}, "offsides": null, "shots": {"total": 1, "on": 1}, "goals": {"total": null, "conceded": 0, "assists": null, "saves": null}, "passes": {"total": 12, "key": 0, "accuracy": "66%"}, "tackles": {"total": 1, "blocks": 0, "interceptions": 1}, "duels": {"total": 24, "won": 7}, "dribbles": {"attempts": 5, "success": 1, "past": 3}, "fouls": {"drawn": 3, "committed": 0}, "cards": {"yellow": 0, "red": 0}, "penalty": {"won": null, "commited": null, "scored": 0, "missed": 0, "saved": null}}]}, {"player": {"id": 166, "name": "Juan Foyth"}, "statistics": [{"games": {"minutes": 15, "number": 21, "position": "D", "rating": "6.4", "captain": false, "substitute": false}, "offsides": null, "shots": {"total": 0, "on": 0}, "goals": {"total": null, "conceded": 0, "assists": null, "saves": null}, "passes": {"total": 5, "key": 0, "accuracy": "83%"}, "tackles": {"total": 1, "blocks": 0, "interceptions": 0}, "duels": {"total": 3, "won": 2}, "dribbles": {"attempts": 1, "success": 0, "past": null}, "fouls": {"drawn": 1, "committed": 0}, "cards": {"yellow": 0, "red": 0}, "penalty": {"won": null, "commited": null, "scored": 0, "missed": 0, "saved": null}}]}, {"player": {"id": 1578, "name": "Giovani Lo Celso"}, "statistics": [{"games": {"minutes": 17, "number": 18, "position": "M", "rating": "6.1", "captain": false, "substitute": false}, "offsides": null, "shots": {"total": 0, "on": 0}, "goals": {"total": null, "conceded": 0, "assists": null, "saves": null}, "passes": {"total": 6, "key": 0, "accuracy": "85%"}, "tackles": {"total": 1, "blocks": 0, "interceptions": 1}, "duels": {"total": 7, "won": 2}, "dribbles": {"attempts": 1, "success": 0, "past": 1}, "fouls": {"drawn": 1, "committed": 1}, "cards": {"yellow": 0, "red": 0}, "penalty": {"won": null, "commited": null, "scored": 0, "missed": 0, "saved": null}}]}, {"player": {"id": 19032, "name": "Ryan Sessegnon"}, "statistics": [{"games": {"minutes": 1, "number": 19, "position": "M", "rating": "\u2013", "captain": false, "substitute": false}, "offsides": null, "shots": {"total": 0, "on": 0}, "goals": {"total": null, "conceded": 0, "assists": null, "saves": null}, "passes": {"total": 0, "key": 0, "accuracy": "0%"}, "tackles": {"total": null, "blocks": 0, "interceptions": 0}, "duels": {"total": 0, "won": 0}, "dribbles": {"attempts": 0, "success": 0, "past": null}, "fouls": {"drawn": 0, "committed": 0}, "cards": {"yellow": 0, "red": 0}, "penalty": {"won": null, "commited": null, "scored": 0, "missed": 0, "saved": null}}]}]}]}]