{"league": {"id": 39, "name": "Premier League", "country": "England", "season": 2013}, "team": {"id": 66, "name": "Aston Villa"}, "form": "WLLLWWDLLDWDDWLLLLDWLDWLLDLWWLLLLDLWLL", "fixtures": {"played": {"home": 19, "away": 19, "total": 38}, "wins": {"home": 6, "away": 4, "total": 10}, "draws": {"home": 3, "away": 5, "total": 8}, "loses": {"home": 10, "away": 10, "total": 20}}, "goals": {"for": {"total": {"home": 22, "away": 17, "total": 39}, "average": {"home": "1.2", "away": "0.9", "total": "1.0"}, "minute": {"0-15": {"total": 9, "percentage": "21.43%"}, "16-30": {"total": 8, "percentage": "19.05%"}, "31-45": {"total": 6, "percentage": "14.29%"}, "46-60": {"total": 3, "percentage": "7.14%"}, "61-75": {"total": 9, "percentage": "21.43%"}, "76-90": {"total": 7, "percentage": "16.67%"}, "91-105": {"total": null, "percentage": null}, "106-120": {"total": null, "percentage": null}}}, "against": {"total": {"home": 29, "away": 32, "total": 61}, "average": {"home": "1.5", "away": "1.7", "total": "1.6"}, "minute": {"0-15": {"total": 8, "percentage": "13.79%"}, "16-30": {"total": 9, "percentage": "15.52%"}, "31-45": {"total": 10, "percentage": "17.24%"}, "46-60": {"total": 9, "percentage": "15.52%"}, "61-75": {"total": 11, "percentage": "18.97%"}, "76-90": {"total": 6, "percentage": "10.34%"}, "91-105": {"total": 5, "percentage": "8.62%"}, "106-120": {"total": null, "percentage": null}}}}, "biggest": {"streak": {"wins": 2, "draws": 2, "loses": 4}, "wins": {"home": "4-1", "away": "1-3"}, "loses": {"home": "1-4", "away": "4-0"}, "goals": {"for": {"home": 4, "away": 3}, "against": {"home": 4, "away": 4}}}, "clean_sheet": {"home": 4, "away": 5, "total": 9}, "failed_to_score": {"home": 8, "away": 8, "total": 16}, "penalty": {"scored": {"total": 2, "percentage": "100.00%"}, "missed": {"total": 0, "percentage": "0%"}, "total": 2}, "lineups": [], "cards": {"yellow": {"0-15": {"total": null, "percentage": null}, "16-30": {"total": null, "percentage": null}, "31-45": {"total": null, "percentage": null}, "46-60": {"total": null, "percentage": null}, "61-75": {"total": null, "percentage": null}, "76-90": {"total": null, "percentage": null}, "91-105": {"total": null, "percentage": null}, "106-120": {"total": null, "percentage": null}}, "red": {"0-15": {"total": null, "percentage": null}, "16-30": {"total": null, "percentage": null}, "31-45": {"total": null, "percentage": null}, "46-60": {"total": null, "percentage": null}, "61-75": {"total": null, "percentage": null}, "76-90": {"total": null, "percentage": null}, "91-105": {"total": null, "percentage": null}, "106-120": {"total": null, "percentage": null}}}}