[{"fixture": {"id": 11904, "referee": "Michael Oliver, England", "timezone": "UTC", "date": "2017-08-12T16:30:00+00:00", "timestamp": 1502555400, "periods": {"first": 1502555400, "second": 1502559000}, "venue": {"id": null, "name": "American Express Community Stadium", "city": "Falmer"}, "status": {"long": "Match Finished", "short": "FT", "elapsed": 90}}, "league": {"id": 39, "name": "Premier League", "country": "England", "season": 2017, "round": "Regular Season - 1"}, "teams": {"home": {"id": 51, "name": "Brighton", "winner": false}, "away": {"id": 50, "name": "Manchester City", "winner": true}}, "goals": {"home": 0, "away": 2}, "score": {"halftime": {"home": 0, "away": 0}, "fulltime": {"home": 0, "away": 2}, "extratime": {"home": null, "away": null}, "penalty": {"home": null, "away": null}}, "events": [{"time": {"elapsed": 24, "extra": null}, "team": {"id": 51, "name": "Brighton"}, "player": {"id": 19135, "name": "I. Brown"}, "assist": {"id": 1762, "name": "J. Murphy"}, "type": "subst", "detail": "Substitution 1", "comments": null}, {"time": {"elapsed": 29, "extra": null}, "team": {"id": 50, "name": "Manchester City"}, "player": {"id": 643, "name": "Gabriel Jesus"}, "assist": {"id": null, "name": null}, "type": "Card", "detail": "Yellow Card", "comments": null}, {"time": {"elapsed": 60, "extra": null}, "team": {"id": 51, "name": "Brighton"}, "player": {"id": 19593, "name": "T. Hemed"}, "assist": {"id": 18982, "name": "G. Murray"}, "type": "subst", "detail": "Substitution 2", "comments": null}, {"time": {"elapsed": 68, "extra": null}, "team": {"id": 50, "name": "Manchester City"}, "player": {"id": 618, "name": "Danilo"}, "assist": {"id": 644, "name": "L. San\u00e9"}, "type": "subst", "detail": "Substitution 1", "comments": null}, {"time": {"elapsed": 70, "extra": null}, "team": {"id": 50, "name": "Manchester City"}, "player": {"id": 642, "name": "S. Ag\u00fcero"}, "assist": {"id": 634, "name": "David Silva"}, "type": "Goal", "detail": "Normal Goal", "comments": null}, {"time": {"elapsed": 75, "extra": null}, "team": {"id": 51, "name": "Brighton"}, "player": {"id": 18973, "name": "S. March"}, "assist": {"id": 18972, "name": "A. Knockaert"}, "type": "subst", "detail": "Substitution 3", "comments": null}, {"time": {"elapsed": 75, "extra": null}, "team": {"id": 50, "name": "Manchester City"}, "player": {"id": 18963, "name": "L. Dunk"}, "assist": {"id": null, "name": null}, "type": "Goal", "detail": "Own Goal", "comments": null}, {"time": {"elapsed": 78, "extra": null}, "team": {"id": 50, "name": "Manchester City"}, "player": {"id": 643, "name": "Gabriel Jesus"}, "assist": {"id": 645, "name": "R. Sterling"}, "type": "subst", "detail": "Substitution 2", "comments": null}, {"time": {"elapsed": 82, "extra": null}, "team": {"id": 50, "name": "Manchester City"}, "player": {"id": 645, "name": "Raheem Sterling"}, "assist": {"id": null, "name": null}, "type": "Card", "detail": "Yellow Card", "comments": null}, {"time": {"elapsed": 83, "extra": null}, "team": {"id": 50, "name": "Manchester City"}, "player": {"id": 642, "name": "S. Ag\u00fcero"}, "assist": {"id": 636, "name": "Bernardo Silva"}, "type": "subst", "detail": "Substitution 3", "comments": null}], "lineups": [{"team": {"id": 51, "name": "Brighton", "colors": null}, "coach": {"id": 2526, "name": "C. Hughton"}, "formation": "4-4-2", "startXI": [{"player": {"id": 2741, "name": "M. Ryan", "number": 1, "pos": "G", "grid": "1:1"}}, {"player": {"id": 18966, "name": "Bruno Saltor", "number": 2, "pos": "D", "grid": "2:4"}}, {"player": {"id": 25454, "name": "M. Suttner", "number": 29, "pos": "D", "grid": "2:3"}}, {"player": {"id": 18962, "name": "S. Duffy", "number": 22, "pos": "D", "grid": "2:2"}}, {"player": {"id": 18963, "name": "L. Dunk", "number": 5, "pos": "D", "grid": "2:1"}}, {"player": {"id": 18977, "name": "D. Stephens", "number": 6, "pos": "M", "grid": "3:4"}}, {"player": {"id": 18970, "name": "P. Gro\u00df", "number": 13, "pos": "F", "grid": "3:3"}}, {"player": {"id": 18975, "name": "D. Pr\u00f6pper", "number": 24, "pos": "M", "grid": "3:2"}}, {"player": {"id": 18973, "name": "S. March", "number": 20, "pos": "M", "grid": "3:1"}}, {"player": {"id": 19593, "name": "T. Hemed", "number": 10, "pos": "F", "grid": "4:2"}}, {"player": {"id": 19135, "name": "I. Brown", "number": 37, "pos": "M", "grid": "4:1"}}], "substitutes": [{"player": {"id": 1762, "name": "J. Murphy", "number": 15, "pos": "F", "grid": null}}, {"player": {"id": 18982, "name": "G. Murray", "number": 17, "pos": "F", "grid": null}}, {"player": {"id": 18972, "name": "A. Knockaert", "number": 11, "pos": "M", "grid": null}}, {"player": {"id": 24819, "name": "U. H\u00fcnemeier", "number": 4, "pos": "D", "grid": null}}, {"player": {"id": 19256, "name": "N. M\u00e4enp\u00e4\u00e4", "number": 12, "pos": "G", "grid": null}}, {"player": {"id": 83018, "name": "S. Sidwell", "number": 14, "pos": "M", "grid": null}}, {"player": {"id": 83020, "name": "L. Rosenior", "number": 23, "pos": "D", "grid": null}}]}, {"team": {"id": 50, "name": "Manchester City", "colors": null}, "coach": {"id": 4, "name": "Guardiola"}, "formation": "3-1-4-2", "startXI": [{"player": {"id": 617, "name": "Ederson Moraes", "number": 31, "pos": "G", "grid": "1:1"}}, {"player": {"id": 621, "name": "V. Kompany", "number": 4, "pos": "D", "grid": "2:3"}}, {"player": {"id": 624, "name": "N. Otamendi", "number": 30, "pos": "D", "grid": "2:2"}}, {"player": {"id": 627, "name": "K. Walker", "number": 2, "pos": "M", "grid": "2:1"}}, {"player": {"id": 618, "name": "Danilo", "number": 3, "pos": "M", "grid": "3:1"}}, {"player": {"id": 626, "name": "J. Stones", "number": 5, "pos": "D", "grid": "4:4"}}, {"player": {"id": 634, "name": "David Silva", "number": 21, "pos": "M", "grid": "4:3"}}, {"player": {"id": 640, "name": "Fernandinho", "number": 25, "pos": "M", "grid": "4:2"}}, {"player": {"id": 629, "name": "K. De Bruyne", "number": 17, "pos": "M", "grid": "4:1"}}, {"player": {"id": 642, "name": "S. Ag\u00fcero", "number": 10, "pos": "F", "grid": "5:2"}}, {"player": {"id": 643, "name": "Gabriel Jesus", "number": 33, "pos": "F", "grid": "5:1"}}], "substitutes": [{"player": {"id": 644, "name": "L. San\u00e9", "number": 19, "pos": "M", "grid": null}}, {"player": {"id": 645, "name": "R. Sterling", "number": 7, "pos": "M", "grid": null}}, {"player": {"id": 636, "name": "Bernardo Silva", "number": 20, "pos": "M", "grid": null}}, {"player": {"id": 614, "name": "C. Bravo", "number": 1, "pos": "G", "grid": null}}, {"player": {"id": 90498, "name": "E. Mangala", "number": 15, "pos": "D", "grid": null}}, {"player": {"id": 90493, "name": "Y. Tour\u00e9", "number": 42, "pos": "M", "grid": null}}, {"player": {"id": 631, "name": "P. Foden", "number": 47, "pos": "M", "grid": null}}]}], "statistics": [{"team": {"id": 51, "name": "Brighton"}, "statistics": [{"type": "Shots on Goal", "value": 2}, {"type": "Shots off Goal", "value": 2}, {"type": "Total Shots", "value": 6}, {"type": "Blocked Shots", "value": 2}, {"type": "Shots insidebox", "value": 4}, {"type": "Shots outsidebox", "value": 2}, {"type": "Fouls", "value": 6}, {"type": "Corner Kicks", "value": 3}, {"type": "Offsides", "value": 6}, {"type": "Ball Possession", "value": "21%"}, {"type": "Yellow Cards", "value": null}, {"type": "Red Cards", "value": null}, {"type": "Goalkeeper Saves", "value": 3}, {"type": "Total passes", "value": 213}, {"type": "Passes accurate", "value": 130}, {"type": "Passes %", "value": "61%"}]}, {"team": {"id": 50, "name": "Manchester City"}, "statistics": [{"type": "Shots on Goal", "value": 4}, {"type": "Shots off Goal", "value": 5}, {"type": "Total Shots", "value": 14}, {"type": "Blocked Shots", "value": 5}, {"type": "Shots insidebox", "value": 7}, {"type": "Shots outsidebox", "value": 8}, {"type": "Fouls", "value": 9}, {"type": "Corner Kicks", "value": 10}, {"type": "Offsides", "value": 1}, {"type": "Ball Possession", "value": "79%"}, {"type": "Yellow Cards", "value": 2}, {"type": "Red Cards", "value": null}, {"type": "Goalkeeper Saves", "value": 2}, {"type": "Total passes", "value": 768}, {"type": "Passes accurate", "value": 691}, {"type": "Passes %", "value": "90%"}]}], "players": [{"team": {"id": 51, "name": "Brighton", "update": "2020-05-12T17:07:13+00:00"}, "players": [{"player": {"id": 2741, "name": "Mathew Ryan"}, "statistics": [{"games": {"minutes": 90, "number": 1, "position": "G", "rating": "6.3", "captain": false, "substitute": false}, "offsides": null, "shots": {"total": 0, "on": 0}, "goals": {"total": null, "conceded": 2, "assists": null, "saves": 3}, "passes": {"total": 13, "key": 0, "accuracy": "48%"}, "tackles": {"total": null, "blocks": 0, "interceptions": 0}, "duels": {"total": 0, "won": 0}, "dribbles": {"attempts": 0, "success": 0, "past": null}, "fouls": {"drawn": 0, "committed": 0}, "cards": {"yellow": 0, "red": 0}, "penalty": {"won": null, "commited": null, "scored": 0, "missed": 0, "saved": 0}}]}, {"player": {"id": 18966, "name": "Bruno Saltor"}, "statistics": [{"games": {"minutes": 90, "number": 2, "position": "D", "rating": "7.1", "captain": true, "substitute": false}, "offsides": null, "shots": {"total": 0, "on": 0}, "goals": {"total": null, "conceded": 0, "assists": null, "saves": null}, "passes": {"total": 17, "key": 0, "accuracy": "68%"}, "tackles": {"total": 1, "blocks": 2, "interceptions": 3}, "duels": {"total": 4, "won": 4}, "dribbles": {"attempts": 1, "success": 1, "past": null}, "fouls": {"drawn": 2, "committed": 0}, "cards": {"yellow": 0, "red": 0}, "penalty": {"won": null, "commited": null, "scored": 0, "missed": 0, "saved": null}}]}, {"player": {"id": 18962, "name": "Shane Duffy"}, "statistics": [{"games": {"minutes": 90, "number": 22, "position": "D", "rating": "6.3", "captain": false, "substitute": false}, "offsides": null, "shots": {"total": 1, "on": 0}, "goals": {"total": null, "conceded": 0, "assists": null, "saves": null}, "passes": {"total": 8, "key": 0, "accuracy": "66%"}, "tackles": {"total": null, "blocks": 1, "interceptions": 0}, "duels": {"total": 0, "won": 0}, "dribbles": {"attempts": 0, "success": 0, "past": null}, "fouls": {"drawn": 0, "committed": 0}, "cards": {"yellow": 0, "red": 0}, "penalty": {"won": null, "commited": null, "scored": 0, "missed": 0, "saved": null}}]}, {"player": {"id": 18963, "name": "Lewis Dunk"}, "statistics": [{"games": {"minutes": 90, "number": 5, "position": "D", "rating": "7.0", "captain": false, "substitute": false}, "offsides": null, "shots": {"total": 3, "on": 2}, "goals": {"total": null, "conceded": 0, "assists": null, "saves": null}, "passes": {"total": 8, "key": 1, "accuracy": "72%"}, "tackles": {"total": null, "blocks": 2, "interceptions": 3}, "duels": {"total": 5, "won": 3}, "dribbles": {"attempts": 0, "success": 0, "past": 1}, "fouls": {"drawn": 1, "committed": 0}, "cards": {"yellow": 0, "red": 0}, "penalty": {"won": null, "commited": null, "scored": 0, "missed": 0, "saved": null}}]}, {"player": {"id": 25454, "name": "Markus Suttner"}, "statistics": [{"games": {"minutes": 90, "number": 29, "position": "D", "rating": "6.7", "captain": false, "substitute": false}, "offsides": null, "shots": {"total": 0, "on": 0}, "goals": {"total": null, "conceded": 0, "assists": null, "saves": null}, "passes": {"total": 12, "key": 0, "accuracy": "66%"}, "tackles": {"total": 2, "blocks": 0, "interceptions": 1}, "duels": {"total": 5, "won": 3}, "dribbles": {"attempts": 1, "success": 0, "past": null}, "fouls": {"drawn": 0, "committed": 0}, "cards": {"yellow": 0, "red": 0}, "penalty": {"won": null, "commited": null, "scored": 0, "missed": 0, "saved": null}}]}, {"player": {"id": 18973, "name": "Solly March"}, "statistics": [{"games": {"minutes": 75, "number": 20, "position": "M", "rating": "6.9", "captain": false, "substitute": false}, "offsides": 1, "shots": {"total": 0, "on": 0}, "goals": {"total": null, "conceded": 0, "assists": null, "saves": null}, "passes": {"total": 14, "key": 0, "accuracy": "77%"}, "tackles": {"total": 2, "blocks": 0, "interceptions": 1}, "duels": {"total": 8, "won": 6}, "dribbles": {"attempts": 2, "success": 2, "past": null}, "fouls": {"drawn": 2, "committed": 1}, "cards": {"yellow": 0, "red": 0}, "penalty": {"won": null, "commited": null, "scored": 0, "missed": 0, "saved": null}}]}, {"player": {"id": 18977, "name": "Dale Stephens"}, "statistics": [{"games": {"minutes": 90, "number": 6, "position": "M", "rating": "6.2", "captain": false, "substitute": false}, "offsides": null, "shots": {"total": 0, "on": 0}, "goals": {"total": null, "conceded": 0, "assists": null, "saves": null}, "passes": {"total": 13, "key": 0, "accuracy": "68%"}, "tackles": {"total": null, "blocks": 0, "interceptions": 3}, "duels": {"total": 9, "won": 2}, "dribbles": {"attempts": 0, "success": 0, "past": 2}, "fouls": {"drawn": 0, "committed": 3}, "cards": {"yellow": 0, "red": 0}, "penalty": {"won": null, "commited": null, "scored": 0, "missed": 0, "saved": null}}]}, {"player": {"id": 18975, "name": "Davy Pr\u00f6pper"}, "statistics": [{"games": {"minutes": 90, "number": 24, "position": "M", "rating": "6.8", "captain": false, "substitute": false}, "offsides": null, "shots": {"total": 2, "on": 0}, "goals": {"total": null, "conceded": 0, "assists": null, "saves": null}, "passes": {"total": 8, "key": 0, "accuracy": "53%"}, "tackles": {"total": 1, "blocks": 0, "interceptions": 1}, "duels": {"total": 5, "won": 3}, "dribbles": {"attempts": 2, "success": 2, "past": 1}, "fouls": {"drawn": 0, "committed": 0}, "cards": {"yellow": 0, "red": 0}, "penalty": {"won": null, "commited": null, "scored": 0, "missed": 0, "saved": null}}]}, {"player": {"id": 19135, "name": "Isaiah Brown"}, "statistics": [{"games": {"minutes": 24, "number": 37, "position": "M", "rating": "6.8", "captain": false, "substitute": false}, "offsides": null, "shots": {"total": 0, "on": 0}, "goals": {"total": null, "conceded": 0, "assists": null, "saves": null}, "passes": {"total": 7, "key": 0, "accuracy": "77%"}, "tackles": {"total": null, "blocks": 0, "interceptions": 0}, "duels": {"total": 2, "won": 2}, "dribbles": {"attempts": 1, "success": 1, "past": null}, "fouls": {"drawn": 0, "committed": 0}, "cards": {"yellow": 0, "red": 0}, "penalty": {"won": null, "commited": null, "scored": 0, "missed": 0, "saved": null}}]}, {"player": {"id": 18970, "name": "Pascal Gro\u00df"}, "statistics": [{"games": {"minutes": 90, "number": 13, "position": "F", "rating": "6.6", "captain": false, "substitute": false}, "offsides": 3, "shots": {"total": 0, "on": 0}, "goals": {"total": null, "conceded": 0, "assists": null, "saves": null}, "passes": {"total": 14, "key": 1, "accuracy": "50%"}, "tackles": {"total": 1, "blocks": 0, "interceptions": 0}, "duels": {"total": 6, "won": 2}, "dribbles": {"attempts": 0, "success": 0, "past": 2}, "fouls": {"drawn": 0, "committed": 0}, "cards": {"yellow": 0, "red": 0}, "penalty": {"won": null, "commited": null, "scored": 0, "missed": 0, "saved": null}}]}, {"player": {"id": 19593, "name": "Tomer Hemed"}, "statistics": [{"games": {"minutes": 60, "number": 10, "position": "F", "rating": "6.4", "captain": false, "substitute": false}, "offsides": null, "shots": {"total": 0, "on": 0}, "goals": {"total": null, "conceded": 0, "assists": null, "saves": null}, "passes": {"total": 5, "key": 0, "accuracy": "33%"}, "tackles": {"total": null, "blocks": 0, "interceptions": 0}, "duels": {"total": 18, "won": 7}, "dribbles": {"attempts": 0, "success": 0, "past": null}, "fouls": {"drawn": 1, "committed": 0}, "cards": {"yellow": 0, "red": 0}, "penalty": {"won": null, "commited": null, "scored": 0, "missed": 0, "saved": null}}]}, {"player": {"id": 18972, "name": "Anthony Knockaert"}, "statistics": [{"games": {"minutes": 15, "number": 11, "position": "M", "rating": "6.7", "captain": false, "substitute": true}, "offsides": null, "shots": {"total": 0, "on": 0}, "goals": {"total": null, "conceded": 0, "assists": null, "saves": null}, "passes": {"total": 2, "key": 0, "accuracy": "50%"}, "tackles": {"total": 1, "blocks": 0, "interceptions": 0}, "duels": {"total": 3, "won": 2}, "dribbles": {"attempts": 1, "success": 0, "past": null}, "fouls": {"drawn": 1, "committed": 0}, "cards": {"yellow": 0, "red": 0}, "penalty": {"won": null, "commited": null, "scored": 0, "missed": 0, "saved": null}}]}, {"player": {"id": 18982, "name": "Glenn Murray"}, "statistics": [{"games": {"minutes": 30, "number": 17, "position": "F", "rating": "6.4", "captain": false, "substitute": true}, "offsides": 1, "shots": {"total": 0, "on": 0}, "goals": {"total": null, "conceded": 0, "assists": null, "saves": null}, "passes": {"total": 3, "key": 0, "accuracy": "75%"}, "tackles": {"total": null, "blocks": 0, "interceptions": 0}, "duels": {"total": 4, "won": 2}, "dribbles": {"attempts": 1, "success": 1, "past": null}, "fouls": {"drawn": 1, "committed": 1}, "cards": {"yellow": 0, "red": 0}, "penalty": {"won": null, "commited": null, "scored": 0, "missed": 0, "saved": null}}]}, {"player": {"id": 1762, "name": "Jamie Murphy"}, "statistics": [{"games": {"minutes": 66, "number": 15, "position": "F", "rating": "6.3", "captain": false, "substitute": true}, "offsides": 1, "shots": {"total": 0, "on": 0}, "goals": {"total": null, "conceded": 0, "assists": null, "saves": null}, "passes": {"total": 6, "key": 0, "accuracy": "75%"}, "tackles": {"total": 2, "blocks": 0, "interceptions": 0}, "duels": {"total": 4, "won": 2}, "dribbles": {"attempts": 0, "success": 0, "past": null}, "fouls": {"drawn": 0, "committed": 1}, "cards": {"yellow": 0, "red": 0}, "penalty": {"won": null, "commited": null, "scored": 0, "missed": 0, "saved": null}}]}]}, {"team": {"id": 50, "name": "Manchester City", "update": "2020-05-12T17:07:13+00:00"}, "players": [{"player": {"id": 617, "name": "Ederson"}, "statistics": [{"games": {"minutes": 90, "number": 31, "position": "G", "rating": "7.1", "captain": false, "substitute": false}, "offsides": null, "shots": {"total": 0, "on": 0}, "goals": {"total": null, "conceded": 0, "assists": null, "saves": 2}, "passes": {"total": 13, "key": 0, "accuracy": "76%"}, "tackles": {"total": null, "blocks": 0, "interceptions": 0}, "duels": {"total": 0, "won": 0}, "dribbles": {"attempts": 0, "success": 0, "past": null}, "fouls": {"drawn": 0, "committed": 0}, "cards": {"yellow": 0, "red": 0}, "penalty": {"won": null, "commited": null, "scored": 0, "missed": 0, "saved": 0}}]}, {"player": {"id": 621, "name": "Vincent Kompany"}, "statistics": [{"games": {"minutes": 90, "number": 4, "position": "D", "rating": "7.5", "captain": true, "substitute": false}, "offsides": null, "shots": {"total": 0, "on": 0}, "goals": {"total": null, "conceded": 0, "assists": null, "saves": null}, "passes": {"total": 79, "key": 0, "accuracy": "90%"}, "tackles": {"total": 1, "blocks": 2, "interceptions": 3}, "duels": {"total": 3, "won": 2}, "dribbles": {"attempts": 0, "success": 0, "past": null}, "fouls": {"drawn": 0, "committed": 0}, "cards": {"yellow": 0, "red": 0}, "penalty": {"won": null, "commited": null, "scored": 0, "missed": 0, "saved": null}}]}, {"player": {"id": 626, "name": "John Stones"}, "statistics": [{"games": {"minutes": 90, "number": 5, "position": "D", "rating": "7.1", "captain": false, "substitute": false}, "offsides": null, "shots": {"total": 0, "on": 0}, "goals": {"total": null, "conceded": 0, "assists": null, "saves": null}, "passes": {"total": 96, "key": 0, "accuracy": "97%"}, "tackles": {"total": null, "blocks": 0, "interceptions": 0}, "duels": {"total": 2, "won": 1}, "dribbles": {"attempts": 0, "success": 0, "past": null}, "fouls": {"drawn": 0, "committed": 1}, "cards": {"yellow": 0, "red": 0}, "penalty": {"won": null, "commited": null, "scored": 0, "missed": 0, "saved": null}}]}, {"player": {"id": 624, "name": "Nicol\u00e1s Otamendi"}, "statistics": [{"games": {"minutes": 90, "number": 30, "position": "D", "rating": "7.6", "captain": false, "substitute": false}, "offsides": null, "shots": {"total": 1, "on": 0}, "goals": {"total": null, "conceded": 0, "assists": null, "saves": null}, "passes": {"total": 94, "key": 0, "accuracy": "92%"}, "tackles": {"total": 1, "blocks": 0, "interceptions": 2}, "duels": {"total": 7, "won": 4}, "dribbles": {"attempts": 0, "success": 0, "past": null}, "fouls": {"drawn": 0, "committed": 1}, "cards": {"yellow": 0, "red": 0}, "penalty": {"won": null, "commited": null, "scored": 0, "missed": 0, "saved": null}}]}, {"player": {"id": 640, "name": "Fernandinho"}, "statistics": [{"games": {"minutes": 90, "number": 25, "position": "M", "rating": "7.1", "captain": false, "substitute": false}, "offsides": null, "shots": {"total": 2, "on": 1}, "goals": {"total": null, "conceded": 0, "assists": null, "saves": null}, "passes": {"total": 86, "key": 1, "accuracy": "86%"}, "tackles": {"total": null, "blocks": 0, "interceptions": 2}, "duels": {"total": 10, "won": 3}, "dribbles": {"attempts": 0, "success": 0, "past": 2}, "fouls": {"drawn": 1, "committed": 0}, "cards": {"yellow": 0, "red": 0}, "penalty": {"won": null, "commited": null, "scored": 0, "missed": 0, "saved": null}}]}, {"player": {"id": 627, "name": "Kyle Walker"}, "statistics": [{"games": {"minutes": 90, "number": 2, "position": "M", "rating": "6.8", "captain": false, "substitute": false}, "offsides": null, "shots": {"total": 0, "on": 0}, "goals": {"total": null, "conceded": 0, "assists": null, "saves": null}, "passes": {"total": 60, "key": 2, "accuracy": "89%"}, "tackles": {"total": 1, "blocks": 0, "interceptions": 0}, "duels": {"total": 10, "won": 5}, "dribbles": {"attempts": 2, "success": 0, "past": null}, "fouls": {"drawn": 1, "committed": 0}, "cards": {"yellow": 0, "red": 0}, "penalty": {"won": null, "commited": null, "scored": 0, "missed": 0, "saved": null}}]}, {"player": {"id": 629, "name": "Kevin De Bruyne"}, "statistics": [{"games": {"minutes": 90, "number": 17, "position": "M", "rating": "7.4", "captain": false, "substitute": false}, "offsides": null, "shots": {"total": 4, "on": 1}, "goals": {"total": null, "conceded": 0, "assists": null, "saves": null}, "passes": {"total": 72, "key": 0, "accuracy": "88%"}, "tackles": {"total": 2, "blocks": 0, "interceptions": 0}, "duels": {"total": 7, "won": 4}, "dribbles": {"attempts": 2, "success": 1, "past": 1}, "fouls": {"drawn": 0, "committed": 0}, "cards": {"yellow": 0, "red": 0}, "penalty": {"won": null, "commited": null, "scored": 0, "missed": 0, "saved": null}}]}, {"player": {"id": 634, "name": "David Silva"}, "statistics": [{"games": {"minutes": 90, "number": 21, "position": "M", "rating": "8.1", "captain": false, "substitute": false}, "offsides": 1, "shots": {"total": 0, "on": 0}, "goals": {"total": null, "conceded": 0, "assists": 1, "saves": null}, "passes": {"total": 94, "key": 5, "accuracy": "93%"}, "tackles": {"total": 1, "blocks": 0, "interceptions": 2}, "duels": {"total": 9, "won": 6}, "dribbles": {"attempts": 1, "success": 1, "past": 2}, "fouls": {"drawn": 3, "committed": 1}, "cards": {"yellow": 0, "red": 0}, "penalty": {"won": null, "commited": null, "scored": 0, "missed": 0, "saved": null}}]}, {"player": {"id": 618, "name": "Danilo"}, "statistics": [{"games": {"minutes": 68, "number": 3, "position": "M", "rating": "6.6", "captain": false, "substitute": false}, "offsides": null, "shots": {"total": 1, "on": 0}, "goals": {"total": null, "conceded": 0, "assists": null, "saves": null}, "passes": {"total": 34, "key": 0, "accuracy": "87%"}, "tackles": {"total": 1, "blocks": 0, "interceptions": 0}, "duels": {"total": 4, "won": 3}, "dribbles": {"attempts": 0, "success": 0, "past": null}, "fouls": {"drawn": 1, "committed": 0}, "cards": {"yellow": 0, "red": 0}, "penalty": {"won": null, "commited": null, "scored": 0, "missed": 0, "saved": null}}]}, {"player": {"id": 642, "name": "Sergio Ag\u00fcero"}, "statistics": [{"games": {"minutes": 83, "number": 10, "position": "F", "rating": "7.3", "captain": false, "substitute": false}, "offsides": null, "shots": {"total": 2, "on": 1}, "goals": {"total": 1, "conceded": 0, "assists": null, "saves": null}, "passes": {"total": 13, "key": 2, "accuracy": "68%"}, "tackles": {"total": 1, "blocks": 0, "interceptions": 0}, "duels": {"total": 5, "won": 2}, "dribbles": {"attempts": 3, "success": 1, "past": null}, "fouls": {"drawn": 0, "committed": 1}, "cards": {"yellow": 0, "red": 0}, "penalty": {"won": null, "commited": null, "scored": 0, "missed": 0, "saved": null}}]}, {"player": {"id": 643, "name": "Gabriel Jesus"}, "statistics": [{"games": {"minutes": 78, "number": 33, "position": "F", "rating": "6.5", "captain": false, "substitute": false}, "offsides": null, "shots": {"total": 4, "on": 1}, "goals": {"total": null, "conceded": 0, "assists": null, "saves": null}, "passes": {"total": 20, "key": 0, "accuracy": "80%"}, "tackles": {"total": 1, "blocks": 0, "interceptions": 0}, "duels": {"total": 8, "won": 3}, "dribbles": {"attempts": 2, "success": 2, "past": 1}, "fouls": {"drawn": 0, "committed": 2}, "cards": {"yellow": 1, "red": 0}, "penalty": {"won": null, "commited": null, "scored": 0, "missed": 0, "saved": null}}]}, {"player": {"id": 645, "name": "Raheem Sterling"}, "statistics": [{"games": {"minutes": 12, "number": 7, "position": "M", "rating": "6.4", "captain": false, "substitute": false}, "offsides": null, "shots": {"total": 0, "on": 0}, "goals": {"total": null, "conceded": 0, "assists": null, "saves": null}, "passes": {"total": 6, "key": 0, "accuracy": "100%"}, "tackles": {"total": null, "blocks": 0, "interceptions": 0}, "duels": {"total": 4, "won": 1}, "dribbles": {"attempts": 1, "success": 1, "past": 1}, "fouls": {"drawn": 0, "committed": 1}, "cards": {"yellow": 1, "red": 0}, "penalty": {"won": null, "commited": null, "scored": 0, "missed": 0, "saved": null}}]}, {"player": {"id": 636, "name": "Bernardo Silva"}, "statistics": [{"games": {"minutes": 7, "number": 20, "position": "M", "rating": "6.6", "captain": false, "substitute": false}, "offsides": null, "shots": {"total": 0, "on": 0}, "goals": {"total": null, "conceded": 0, "assists": null, "saves": null}, "passes": {"total": 12, "key": 0, "accuracy": "85%"}, "tackles": {"total": null, "blocks": 0, "interceptions": 0}, "duels": {"total": 0, "won": 0}, "dribbles": {"attempts": 0, "success": 0, "past": null}, "fouls": {"drawn": 0, "committed": 0}, "cards": {"yellow": 0, "red": 0}, "penalty": {"won": null, "commited": null, "scored": 0, "missed": 0, "saved": null}}]}, {"player": {"id": 644, "name": "Leroy San\u00e9"}, "statistics": [{"games": {"minutes": 22, "number": 19, "position": "M", "rating": "6.4", "captain": false, "substitute": false}, "offsides": null, "shots": {"total": 0, "on": 0}, "goals": {"total": null, "conceded": 0, "assists": null, "saves": null}, "passes": {"total": 12, "key": 0, "accuracy": "100%"}, "tackles": {"total": 1, "blocks": 0, "interceptions": 0}, "duels": {"total": 4, "won": 1}, "dribbles": {"attempts": 1, "success": 0, "past": null}, "fouls": {"drawn": 0, "committed": 2}, "cards": {"yellow": 0, "red": 0}, "penalty": {"won": null, "commited": null, "scored": 0, "missed": 0, "saved": null}}]}]}]}]